<?xml version="1.0" encoding="utf-8"?>
<psmMeta npTitleId="NPOA00235_00">

  <appVersion>1.30</appVersion>
  <runtimeVersion>1.21</runtimeVersion>
  <packageSize>42367328</packageSize>
  <localizedMetadataList default_locale="en_GB"><localizedMeta locale="en_AU"><description><![CDATA[Ele-Mental is a crazy fast paced arcade game, from HyperThetical Games.<BR>Absorb and avoid incoming Ele-Ments by changing to the right colours.<BR>Simple Concept, Challenging Gameplay<BR><BR>There are 12 survival game modes and 3 multiple level Arcade modes.<BR>Loads to Unlock, Stat Tracking and High Scores keep you coming back for more.<BR>One loading screen so you can get straight back in the action, no messing about.<BR><BR>If you like a challenge e-mail pics of your scores to us for a place on our website.<BR><BR>*Update 1.01 Includes PlayStation®TV compatibility and a rewrite of the uber-classic tune.<BR>*Update 1.30 Brings by popular demand, PlayStation® colour control scheme. <BR>Also Ele-Medals. 20 challenges of varying difficulty from bronze to platinum. <BR>These will put the most seasoned Ele-Mentalists to the test. <BR><BR>Package size: 41 MB - More storage space required for install<BR><BR>Compatibility information:<BR>Number of players for local play: 1 Player<BR><BR>Supported interfaces/sensors<BR>- Touchscreen<BR>- Controller / On-screen controller<BR><BR>Supported languages:<BR>English(United States)/English(United Kingdom)<BR><BR>Chris Maule<BR><BR>]]></description></localizedMeta><localizedMeta locale="en_CA"><description><![CDATA[Ele-Mental is a crazy fast paced arcade game, from HyperThetical Games.<BR>Absorb and avoid incoming Ele-Ments by changing to the right colours.<BR>Simple Concept, Challenging Gameplay<BR><BR>There are 12 survival game modes and 3 multiple level Arcade modes.<BR>Loads to Unlock, Stat Tracking and High Scores keep you coming back for more.<BR>One loading screen so you can get straight back in the action, no messing about.<BR><BR>If you like a challenge e-mail pics of your scores to us for a place on our website.<BR><BR>*Update 1.01 Includes PlayStation®TV compatibility and a rewrite of the uber-classic tune.<BR>*Update 1.30 Brings by popular demand, PlayStation® colour control scheme. <BR>Also Ele-Medals. 20 challenges of varying difficulty from bronze to platinum. <BR>These will put the most seasoned Ele-Mentalists to the test. <BR><BR>Package size: 41 MB - More storage space required for install<BR><BR>Compatibility information:<BR>Number of players for local play: 1 Player<BR><BR>Supported interfaces/sensors<BR>- Touchscreen<BR>- Controller / On-screen controller<BR><BR>Supported languages:<BR>English(United States)/English(United Kingdom)<BR><BR>Chris Maule<BR><BR>]]></description></localizedMeta><localizedMeta locale="en_GB"><description><![CDATA[Ele-Mental is a crazy fast paced arcade game, from HyperThetical Games.<BR>Absorb and avoid incoming Ele-Ments by changing to the right colours.<BR>Simple Concept, Challenging Gameplay<BR><BR>There are 12 survival game modes and 3 multiple level Arcade modes.<BR>Loads to Unlock, Stat Tracking and High Scores keep you coming back for more.<BR>One loading screen so you can get straight back in the action, no messing about.<BR><BR>If you like a challenge e-mail pics of your scores to us for a place on our website.<BR><BR>*Update 1.01 Includes PlayStation®TV compatibility and a rewrite of the uber-classic tune.<BR>*Update 1.30 Brings by popular demand, PlayStation® colour control scheme. <BR>Also Ele-Medals. 20 challenges of varying difficulty from bronze to platinum. <BR>These will put the most seasoned Ele-Mentalists to the test. <BR><BR>Package size: 41 MB - More storage space required for install<BR><BR>Compatibility information:<BR>Number of players for local play: 1 Player<BR><BR>Supported interfaces/sensors<BR>- Touchscreen<BR>- Controller / On-screen controller<BR><BR>Supported languages:<BR>English(United States)/English(United Kingdom)<BR><BR>Chris Maule<BR><BR>]]></description></localizedMeta><localizedMeta locale="en"><description><![CDATA[Ele-Mental is a crazy fast paced arcade game, from HyperThetical Games.<BR>Absorb and avoid incoming Ele-Ments by changing to the right colours.<BR>Simple Concept, Challenging Gameplay<BR><BR>There are 12 survival game modes and 3 multiple level Arcade modes.<BR>Loads to Unlock, Stat Tracking and High Scores keep you coming back for more.<BR>One loading screen so you can get straight back in the action, no messing about.<BR><BR>If you like a challenge e-mail pics of your scores to us for a place on our website.<BR><BR>*Update 1.01 Includes PlayStation®TV compatibility and a rewrite of the uber-classic tune.<BR>**Update 1.30 Brings by popular demand, PlayStation® color control scheme. <BR>Also Ele-Medals. 20 challenges of varying difficulty from bronze to platinum. <BR>These will put the most seasoned Ele-Mentalists to the test. <BR><BR>Package size: 41 MB - More storage space required for install<BR><BR>Compatibility information:<BR>Number of players for local play: 1 Player<BR><BR>Supported interfaces/sensors<BR>- Touchscreen<BR>- Controller / On-screen controller<BR><BR>Supported languages:<BR>English(United States)/English(United Kingdom)<BR><BR>Chris Maule<BR><BR>]]></description></localizedMeta><localizedMeta locale="fr_CA"><description><![CDATA[Ele-mentale est un jeu rapide fou d'arcade .<BR>Construit par un hardcore gamer , spécifiquement pour les hardcore gamers .<BR>Changez couleur d'absorber commune Ele- Ments tout en évitant d'autres .<BR>Il est plus impitoyable , et pourtant incroyablement enrichissante .<BR><BR>Avec beaucoup de choses à débloquer et des scores élevés pour chaque mode de jeu, vous pouvez vous-même et d'autres contester . <BR><BR>Taille du programme : 41 Mo - Plus d’espace de stockage est requis pour l’installation<BR><BR>Information sur la compatibilité :<BR>Nombre de joueurs pour le jeu local : 1 joueur<BR><BR>Interfaces / capteurs compatibles<BR>- Écran tactile<BR>- Manette / Manette d’écran<BR><BR>Langues prises en charge :<BR>Anglais(États-Unis)/Anglais(Royaume-Uni)<BR><BR>Chris Maule<BR><BR>]]></description></localizedMeta><localizedMeta locale="fr"><description><![CDATA[Ele-mentale est un jeu rapide fou d'arcade .<BR>Construit par un hardcore gamer , spécifiquement pour les hardcore gamers .<BR>Changez couleur d'absorber commune Ele- Ments tout en évitant d'autres .<BR>Il est plus impitoyable , et pourtant incroyablement enrichissante .<BR><BR>Avec beaucoup de choses à débloquer et des scores élevés pour chaque mode de jeu, vous pouvez vous-même et d'autres contester . <BR><BR>Taille du paquet : 41 Mo - Nécessite un plus grand espace de stockage pour l’installation<BR><BR>Informations sur la compatibilité :<BR>Nombre de joueurs pour jeu local : 1 joueur<BR><BR>Interfaces/détecteurs pris en charge<BR>- Écran tactile<BR>- Manette / Manette à l’écran<BR><BR>Langues prises en charge :<BR>Anglais(États-Unis)/Anglais(Royaume-Uni)<BR><BR>Chris Maule<BR><BR>]]></description></localizedMeta><localizedMeta locale="ja"><description><![CDATA[Ele- Mentaru  はクレイジー速いペースでアーケードゲームです。<BR>特にハードコアなゲーマーのための、筋金入りのゲーマーによって建てられた。<BR>色を変更し。要素を吸す。敵を避け<BR>それは、最も容赦のない、とまだ​​信じられないほどやりがいがある。<BR><BR>各ゲームモードのロックを解除するたくさんと高得点を使用すると、自分と他人に挑戦することができます。 <BR><BR>コンテンツ容量: 41 MB <BR><BR>プレイ人数: 1人<BR><BR>対応機能:<BR>- タッチスクリーン<BR>- コントローラーまたは、オンスクリーンコントローラー<BR><BR>対応言語:<BR>英語(アメリカ)/英語(イギリス)<BR><BR>著作権等:<BR>Chris Maule<BR><BR>]]></description></localizedMeta></localizedMetadataList>
  <genreList><genre value="Games:Arcade"/><genre value="Games:Unique"/></genreList>
  <ratingList default="SELF"><rating type="PEGIEX"><ratingLogo>PEGIEX_3.png</ratingLogo></rating><rating type="SELF"><ratingLogo>SELF_3.png</ratingLogo></rating><rating type="ESRB"><ratingLogo>ESRB_3.png</ratingLogo></rating></ratingList>
  <screenShotList><screenShot>screenshot_13.png</screenShot><screenShot>screenshot_10.png</screenShot><screenShot>screenshot_12.png</screenShot><screenShot>screenshot_4.png</screenShot><screenShot>screenshot_8.png</screenShot><screenShot>screenshot_11.png</screenShot><screenShot>screenshot_7.png</screenShot><screenShot>screenshot_5.png</screenShot><screenShot>screenshot_6.png</screenShot></screenShotList>

</psmMeta>
