<?xml version="1.0" encoding="utf-8"?>
<psmMeta npTitleId="NPOA00209_00">

  <appVersion>1.00</appVersion>
  <runtimeVersion>4.03</runtimeVersion>
  <packageSize>32252176</packageSize>
  <localizedMetadataList default_locale="en"><localizedMeta locale="en_AU"><description><![CDATA[THIS CONTENT IS NOT COMPATIBLE WITH Android™ DEVICES.<BR><BR>This is the first game I've made for the PlayStation®Vita and also the first game I've ever made using Unity, my first game ever! Feedback would be great.<BR><BR>I will be adding things later on and also report bugs to my Steam account! http://steamcommunity.com/id/zeshirky/ Thanks!<BR><BR>Controls/how to play: <BR>Their is no score limit so you can go crazy! Best to play with a friend (hopefully if you have one) ;) And not yourself.<BR><BR>Press the reset button to.. Well, reset the score!<BR>To move the left player use D Pad up and D Pad down<BR>To move the right player use Triangle to move up and X to move down <BR><BR>Package size: 31 MB - More storage space required for install<BR><BR>Compatibility information:<BR>Number of players for local play: 1-2 Players<BR><BR>Supported interfaces/sensors<BR>- Touchscreen<BR>- Controller / On-screen controller<BR><BR>Supported languages:<BR>English(United States)/English(United Kingdom)<BR><BR>ZeCopyright<BR><BR>Android is a trademark of Google Inc.<BR><BR>]]></description></localizedMeta><localizedMeta locale="en_CA"><description><![CDATA[THIS CONTENT IS NOT COMPATIBLE WITH Android™ DEVICES.<BR><BR>This is the first game I've made for the PlayStation®Vita and also the first game I've ever made using Unity, my first game ever! Feedback would be great.<BR><BR>I will be adding things later on and also report bugs to my Steam account! http://steamcommunity.com/id/zeshirky/ Thanks!<BR><BR>Controls/how to play: <BR>Their is no score limit so you can go crazy! Best to play with a friend (hopefully if you have one) ;) And not yourself.<BR><BR>Press the reset button to.. Well, reset the score!<BR>To move the left player use D Pad up and D Pad down<BR>To move the right player use Triangle to move up and X to move down <BR><BR>Package size: 31 MB - More storage space required for install<BR><BR>Compatibility information:<BR>Number of players for local play: 1-2 Players<BR><BR>Supported interfaces/sensors<BR>- Touchscreen<BR>- Controller / On-screen controller<BR><BR>Supported languages:<BR>English(United States)/English(United Kingdom)<BR><BR>ZeCopyright<BR><BR>Android is a trademark of Google Inc.<BR><BR>]]></description></localizedMeta><localizedMeta locale="en_GB"><description><![CDATA[THIS CONTENT IS NOT COMPATIBLE WITH Android™ DEVICES.<BR><BR>This is the first game I've made for the PlayStation®Vita and also the first game I've ever made using Unity, my first game ever! Feedback would be great.<BR><BR>I will be adding things later on and also report bugs to my Steam account! http://steamcommunity.com/id/zeshirky/ Thanks!<BR><BR>Controls/how to play: <BR>Their is no score limit so you can go crazy! Best to play with a friend (hopefully if you have one) ;) And not yourself.<BR><BR>Press the reset button to.. Well, reset the score!<BR>To move the left player use D Pad up and D Pad down<BR>To move the right player use Triangle to move up and X to move down <BR><BR>Package size: 31 MB - More storage space required for install<BR><BR>Compatibility information:<BR>Number of players for local play: 1-2 Players<BR><BR>Supported interfaces/sensors<BR>- Touchscreen<BR>- Controller / On-screen controller<BR><BR>Supported languages:<BR>English(United States)/English(United Kingdom)<BR><BR>ZeCopyright<BR><BR>Android is a trademark of Google Inc.<BR><BR>]]></description></localizedMeta><localizedMeta locale="en"><description><![CDATA[THIS CONTENT IS NOT COMPATIBLE WITH Android™ DEVICES.<BR><BR>This is the first game I've made for the PlayStation®Vita and also the first game I've ever made using Unity, my first game ever! Feedback would be great.<BR><BR>I will be adding things later on and also report bugs to my Steam account! http://steamcommunity.com/id/zeshirky/ Thanks!<BR><BR>Controls/how to play: <BR>Their is no score limit so you can go crazy! Best to play with a friend (hopefully if you have one) ;) And not yourself.<BR><BR>Press the reset button to.. Well, reset the score!<BR>To move the left player use D Pad up and D Pad down<BR>To move the right player use Triangle to move up and X to move down <BR><BR>Package size: 31 MB - More storage space required for install<BR><BR>Compatibility information:<BR>Number of players for local play: 1-2 Players<BR><BR>Supported interfaces/sensors<BR>- Touchscreen<BR>- Controller / On-screen controller<BR><BR>Supported languages:<BR>English(United States)/English(United Kingdom)<BR><BR>ZeCopyright<BR><BR>Android is a trademark of Google Inc.<BR><BR>]]></description></localizedMeta><localizedMeta locale="fr"><description><![CDATA[CE CONTENU N'EST PAS COMPATIBLE AVEC LES PÉRIPHÉRIQUES Android™.<BR><BR>Ceci est le premier jeu que je l'ai fait pour la PlayStation®Vita et aussi le premier jeu que je ai jamais fait avec Unity, mon premier jeu! Commentaires serait formidable. <BR><BR>Je vais ajouter des choses plus tard et signaler les bugs aussi à mon compte Steam! http://steamcommunity.com/id/zeshirky/ Merci! <BR><BR>Commandes / comment jouer: <BR>Leur a pas de limite de score que vous pouvez devenir fou! Le mieux est de jouer avec un ami (espérons-le si vous en avez un);) Et pas vous-même. <BR><BR>Appuyez sur le bouton de remise à zéro .. Eh bien, réinitialiser le score! <BR>Pour déplacer le joueur à gauche utilisation D Pad et D Pad vers le bas <BR>Pour déplacer le joueur de droite utiliser Triangle à monter et à descendre X <BR><BR>Taille du paquet : 31 Mo - Nécessite un plus grand espace de stockage pour l’installation<BR><BR>Informations sur la compatibilité :<BR>Nombre de joueurs pour jeu local : 1-2 joueurs<BR><BR>Interfaces/détecteurs pris en charge<BR>- Écran tactile<BR>- Manette / Manette à l’écran<BR><BR>Langues prises en charge :<BR>Anglais(États-Unis)/Anglais(Royaume-Uni)<BR><BR>ZeCopyright<BR><BR>Android is a trademark of Google Inc.<BR><BR>]]></description></localizedMeta></localizedMetadataList>
  <genreList><genre value="Games:Arcade"/></genreList>
  <ratingList default="SELF"><rating type="PEGIEX"><ratingLogo>PEGIEX_3.png</ratingLogo></rating><rating type="SELF"><ratingLogo>SELF_3.png</ratingLogo></rating><rating type="ESRB"><ratingLogo>ESRB_3.png</ratingLogo></rating></ratingList>
  <screenShotList><screenShot>screenshot_3.png</screenShot><screenShot>screenshot_4.png</screenShot><screenShot>screenshot_5.png</screenShot></screenShotList>

</psmMeta>
