<?xml version="1.0" encoding="utf-8"?>
<psmMeta npTitleId="NPNA00291_00">

  <appVersion>1.00</appVersion>
  <runtimeVersion>2.00</runtimeVersion>
  <packageSize>65770416</packageSize>
  <localizedMetadataList default_locale="en"><localizedMeta locale="en_AU"><description><![CDATA[THIS CONTENT IS NOT COMPATIBLE WITH Android™ DEVICES.<BR><BR>As the Firewall Program on a computer defend your system from a variety of online risks. Control your ship and shoot down all manner of malware from corrupting your valuable download. Use your abilities to speed yourself up or slow down your enemies before they make it to the other side. <BR><BR>Package size: 63 MB - More storage space required for install<BR><BR>Compatibility information:<BR>Number of players for local play: 1 Player<BR><BR>Supported interfaces/sensors<BR>- Touchscreen<BR>- Controller / On-screen controller<BR><BR>Supported languages:<BR>English(United States)/English(United Kingdom)<BR><BR>Copyright (C) 2015 Ka Wa Yan. All Rights Reserved.<BR><BR>Android is a trademark of Google Inc.<BR><BR>]]></description></localizedMeta><localizedMeta locale="en_CA"><description><![CDATA[THIS CONTENT IS NOT COMPATIBLE WITH Android™ DEVICES.<BR><BR>As the Firewall Program on a computer defend your system from a variety of online risks. Control your ship and shoot down all manner of malware from corrupting your valuable download. Use your abilities to speed yourself up or slow down your enemies before they make it to the other side. <BR><BR>Package size: 63 MB - More storage space required for install<BR><BR>Compatibility information:<BR>Number of players for local play: 1 Player<BR><BR>Supported interfaces/sensors<BR>- Touchscreen<BR>- Controller / On-screen controller<BR><BR>Supported languages:<BR>English(United States)/English(United Kingdom)<BR><BR>Copyright (C) 2015 Ka Wa Yan. All Rights Reserved.<BR><BR>Android is a trademark of Google Inc.<BR><BR>]]></description></localizedMeta><localizedMeta locale="en_GB"><description><![CDATA[THIS CONTENT IS NOT COMPATIBLE WITH Android™ DEVICES.<BR><BR>As the Firewall Program on a computer defend your system from a variety of online risks. Control your ship and shoot down all manner of malware from corrupting your valuable download. Use your abilities to speed yourself up or slow down your enemies before they make it to the other side. <BR><BR>Package size: 63 MB - More storage space required for install<BR><BR>Compatibility information:<BR>Number of players for local play: 1 Player<BR><BR>Supported interfaces/sensors<BR>- Touchscreen<BR>- Controller / On-screen controller<BR><BR>Supported languages:<BR>English(United States)/English(United Kingdom)<BR><BR>Copyright (C) 2015 Ka Wa Yan. All Rights Reserved.<BR><BR>Android is a trademark of Google Inc.<BR><BR>]]></description></localizedMeta><localizedMeta locale="en"><description><![CDATA[THIS CONTENT IS NOT COMPATIBLE WITH Android™ DEVICES.<BR><BR>As the Firewall Program on a computer defend your system from a variety of online risks. Control your ship and shoot down all manner of malware from corrupting your valuable download. Use your abilities to speed yourself up or slow down your enemies before they make it to the other side. <BR><BR>Package size: 63 MB - More storage space required for install<BR><BR>Compatibility information:<BR>Number of players for local play: 1 Player<BR><BR>Supported interfaces/sensors<BR>- Touchscreen<BR>- Controller / On-screen controller<BR><BR>Supported languages:<BR>English(United States)/English(United Kingdom)<BR><BR>Copyright (C) 2015 Ka Wa Yan. All Rights Reserved.<BR><BR>Android is a trademark of Google Inc.<BR><BR>]]></description></localizedMeta><localizedMeta locale="fr_CA"><description><![CDATA[CE CONTENU N'EST PAS COMPATIBLE AVEC LES PÉRIPHÉRIQUES Android™.<BR><BR>en tant que la pare-feu programme d'ordinateur protéger votre système <BR><BR>Taille du programme : 63 Mo - Plus d’espace de stockage est requis pour l’installation<BR><BR>Information sur la compatibilité :<BR>Nombre de joueurs pour le jeu local : 1 joueur<BR><BR>Interfaces / capteurs compatibles<BR>- Écran tactile<BR>- Manette / Manette d’écran<BR><BR>Langues prises en charge :<BR>Anglais(États-Unis)/Anglais(Royaume-Uni)<BR><BR>Copyright (C) 2015 Ka Wa Yan. All Rights Reserved.<BR><BR>Android is a trademark of Google Inc.<BR><BR>]]></description></localizedMeta></localizedMetadataList>
  <genreList><genre value="Games:Shooter"/></genreList>
  <ratingList default="SELF"><rating type="PEGIEX"><ratingLogo>PEGIEX_12.png</ratingLogo><contentDescriptor>PEGIEX_Violence.png</contentDescriptor></rating><rating type="SELF"><ratingLogo>SELF_7.png</ratingLogo><contentDescriptor>SELF_Violence.png</contentDescriptor></rating><rating type="ESRB"><ratingLogo>ESRB_10.png</ratingLogo></rating></ratingList>
  <screenShotList><screenShot>screenshot_6.png</screenShot><screenShot>screenshot_2.png</screenShot><screenShot>screenshot_3.png</screenShot></screenShotList>

</psmMeta>
